{
    "Altersvorsorgeberatung": {
        "de": "Altersvorsorgeberatung",
        "en": "Retirement Planning",
        "es": "Planificación de jubilación"
    },
    "Arbeitsrechtliche Beratung": {
        "de": "Arbeitsrechtliche Beratung",
        "en": "Employment Law Consulting",
        "es": "Asesoría laboral"
    },
    "Baufinanzierungsberatung": {
        "de": "Baufinanzierungsberatung",
        "en": "Construction Financing Consulting",
        "es": "Asesoría en financiación de construcción"
    },
    "Bauprojektberatung": {
        "de": "Bauprojektberatung",
        "en": "Construction Project Consulting",
        "es": "Asesoría en proyectos de construcción"
    },
    "Betriebliches Gesundheitsmanagement": {
        "de": "Betriebliches Gesundheitsmanagement",
        "en": "Corporate Health Management",
        "es": "Gestión de salud corporativa"
    },
    "Betriebshaftpflichtversicherung": {
        "de": "Betriebshaftpflichtversicherung",
        "en": "Public Liability Insurance",
        "es": "Seguro de responsabilidad civil"
    },
    "Betriebsunterbrechungsversicherung": {
        "de": "Betriebsunterbrechungsversicherung",
        "en": "Business Interruption Insurance",
        "es": "Seguro de interrupción de negocios"
    },
    "Buchhaltungsberatung": {
        "de": "Buchhaltungsberatung",
        "en": "Accounting Consulting",
        "es": "Asesoría contable"
    },
    "Change Management": {
        "de": "Change Management",
        "en": "Change Management",
        "es": "Gestión del cambio"
    },
    "Cloud-Beratung": {
        "de": "Cloud-Beratung",
        "en": "Cloud Consulting",
        "es": "Consultoría en la nube"
    },
    "Coaching-Dienstleistungen": {
        "de": "Coaching-Dienstleistungen",
        "en": "Coaching Services",
        "es": "Servicios de coaching"
    },
    "Compliance-Beratung": {
        "de": "Compliance-Beratung",
        "en": "Compliance Consulting",
        "es": "Consultoría de cumplimiento"
    },
    "Customer Service-Beratung": {
        "de": "Customer Service-Beratung",
        "en": "Customer Service Consulting",
        "es": "Consultoría de servicio al cliente"
    },
    "Datenschutz-Schulungen": {
        "de": "Datenschutz-Schulungen",
        "en": "Data Protection Training",
        "es": "Formación en protección de datos"
    },
    "Datenschutzberatung": {
        "de": "Datenschutzberatung",
        "en": "Data Protection Consulting",
        "es": "Consultoría de protección de datos"
    },
    "Digitalisierung in der Industrie": {
        "de": "Digitalisierung in der Industrie",
        "en": "Industrial Digitalization",
        "es": "Digitalización industrial"
    },
    "Digitale Transformation": {
        "de": "Digitale Transformation",
        "en": "Digital Transformation",
        "es": "Transformación digital"
    },
    "E-Commerce-Beratung": {
        "de": "E-Commerce-Beratung",
        "en": "E-Commerce Consulting",
        "es": "Consultoría de comercio electrónico"
    },
    "Energieberatung": {
        "de": "Energieberatung",
        "en": "Energy Consulting",
        "es": "Consultoría energética"
    },
    "Finanzberatung": {
        "de": "Finanzberatung",
        "en": "Financial Consulting",
        "es": "Asesoría financiera"
    },
    "Flottenversicherungsberatung": {
        "de": "Flottenversicherungsberatung",
        "en": "Fleet Insurance Consulting",
        "es": "Asesoría en seguros de flotas"
    },
    "Fusions- und Übernahmeberatung": {
        "de": "Fusions- und Übernahmeberatung",
        "en": "M&A Consulting",
        "es": "Consultoría de fusiones y adquisiciones"
    },
    "Geschäftsberatung": {
        "de": "Geschäftsberatung",
        "en": "Business Consulting",
        "es": "Consultoría de negocios"
    },
    "Haftpflichtversicherungsberatung": {
        "de": "Haftpflichtversicherungsberatung",
        "en": "Liability Insurance Consulting",
        "es": "Asesoría en seguros de responsabilidad"
    },
    "Imageberatung": {
        "de": "Imageberatung",
        "en": "Image Consulting",
        "es": "Asesoría de imagen"
    },
    "Innovationsberatung": {
        "de": "Innovationsberatung",
        "en": "Innovation Consulting",
        "es": "Consultoría de innovación"
    },
    "IT-Beratung": {
        "de": "IT-Beratung",
        "en": "IT Consulting",
        "es": "Consultoría TI"
    },
    "IT-Sicherheitsberatung": {
        "de": "IT-Sicherheitsberatung",
        "en": "IT Security Consulting",
        "es": "Consultoría de seguridad TI"
    },
    "Kapitalanlageberatung": {
        "de": "Kapitalanlageberatung",
        "en": "Investment Consulting",
        "es": "Asesoría de inversiones"
    },
    "Kommunikationsberatung": {
        "de": "Kommunikationsberatung",
        "en": "Communications Consulting",
        "es": "Consultoría de comunicación"
    },
    "Kostenoptimierung": {
        "de": "Kostenoptimierung",
        "en": "Cost Optimization",
        "es": "Optimización de costes"
    },
    "Krisenmanagement-Beratung": {
        "de": "Krisenmanagement-Beratung",
        "en": "Crisis Management Consulting",
        "es": "Consultoría de gestión de crisis"
    },
    "Kulturwandel-Beratung": {
        "de": "Kulturwandel-Beratung",
        "en": "Cultural Change Consulting",
        "es": "Consultoría de cambio cultural"
    },
    "Kurierdienste": {
        "de": "Kurierdienste",
        "en": "Courier Services",
        "es": "Servicios de mensajería"
    },
    "Krankenversicherungsberatung": {
        "de": "Krankenversicherungsberatung",
        "en": "Health Insurance Consulting",
        "es": "Asesoría de seguros de salud"
    },
    "Leitbildentwicklung": {
        "de": "Leitbildentwicklung",
        "en": "Mission Statement Development",
        "es": "Desarrollo de misión corporativa"
    },
    "Lebensversicherungsberatung": {
        "de": "Lebensversicherungsberatung",
        "en": "Life Insurance Consulting",
        "es": "Asesoría de seguros de vida"
    },
    "Logistikberatung": {
        "de": "Logistikberatung",
        "en": "Logistics Consulting",
        "es": "Consultoría logística"
    },
    "Marketingberatung": {
        "de": "Marketingberatung",
        "en": "Marketing Consulting",
        "es": "Consultoría de marketing"
    },
    "Nachhaltige Energieprojekte": {
        "de": "Nachhaltige Energieprojekte",
        "en": "Sustainable Energy Projects",
        "es": "Proyectos de energía sostenible"
    },
    "Nachhaltigkeitsberatung": {
        "de": "Nachhaltigkeitsberatung",
        "en": "Sustainability Consulting",
        "es": "Consultoría de sostenibilidad"
    },
    "Organisationsberatung": {
        "de": "Organisationsberatung",
        "en": "Organizational Consulting",
        "es": "Consultoría organizacional"
    },
    "Pflegeversicherungsberatung": {
        "de": "Pflegeversicherungsberatung",
        "en": "Care Insurance Consulting",
        "es": "Asesoría de seguros de cuidado"
    },
    "Private Krankenversicherung": {
        "de": "Private Krankenversicherung",
        "en": "Private Health Insurance",
        "es": "Seguro médico privado"
    },
    "Produktentwicklung": {
        "de": "Produktentwicklung",
        "en": "Product Development",
        "es": "Desarrollo de productos"
    },
    "Produktionsoptimierung": {
        "de": "Produktionsoptimierung",
        "en": "Production Optimization",
        "es": "Optimización de producción"
    },
    "Produktionsplanung": {
        "de": "Produktionsplanung",
        "en": "Production Planning",
        "es": "Planificación de producción"
    },
    "Prozessoptimierung": {
        "de": "Prozessoptimierung",
        "en": "Process Optimization",
        "es": "Optimización de procesos"
    },
    "Projektmanagement-Beratung": {
        "de": "Projektmanagement-Beratung",
        "en": "Project Management Consulting",
        "es": "Consultoría de gestión de proyectos"
    },
    "Rechtsschutzversicherungsberatung": {
        "de": "Rechtsschutzversicherungsberatung",
        "en": "Legal Protection Insurance Consulting",
        "es": "Asesoría de seguros de protección legal"
    },
    "Reiseversicherungsberatung": {
        "de": "Reiseversicherungsberatung",
        "en": "Travel Insurance Consulting",
        "es": "Asesoría de seguros de viaje"
    },
    "Rentenversicherungsberatung": {
        "de": "Rentenversicherungsberatung",
        "en": "Pension Insurance Consulting",
        "es": "Asesoría de seguros de pensiones"
    },
    "Risikomanagement-Beratung": {
        "de": "Risikomanagement-Beratung",
        "en": "Risk Management Consulting",
        "es": "Consultoría de gestión de riesgos"
    },
    "Schuldenberatung": {
        "de": "Schuldenberatung",
        "en": "Debt Counseling",
        "es": "Asesoría de deudas"
    },
    "Steuerberatung": {
        "de": "Steuerberatung",
        "en": "Tax Consulting",
        "es": "Asesoría fiscal"
    },
    "Steuerplanung": {
        "de": "Steuerplanung",
        "en": "Tax Planning",
        "es": "Planificación fiscal"
    },
    "Strategieberatung": {
        "de": "Strategieberatung",
        "en": "Strategy Consulting",
        "es": "Consultoría estratégica"
    },
    "Strategische Marktanalyse": {
        "de": "Strategische Marktanalyse",
        "en": "Strategic Market Analysis",
        "es": "Análisis estratégico de mercado"
    },
    "Supply-Chain-Beratung": {
        "de": "Supply-Chain-Beratung",
        "en": "Supply Chain Consulting",
        "es": "Consultoría de cadena de suministro"
    },
    "Technologie-Investitionen": {
        "de": "Technologie-Investitionen",
        "en": "Technology Investments",
        "es": "Inversiones tecnológicas"
    },
    "Technologieberatung": {
        "de": "Technologieberatung",
        "en": "Technology Consulting",
        "es": "Consultoría tecnológica"
    },
    "Todesfallversicherungsberatung": {
        "de": "Todesfallversicherungsberatung",
        "en": "Death Benefit Insurance Consulting",
        "es": "Asesoría de seguros por fallecimiento"
    },
    "Umweltberatung": {
        "de": "Umweltberatung",
        "en": "Environmental Consulting",
        "es": "Consultoría ambiental"
    },
    "Unternehmensberatung": {
        "de": "Unternehmensberatung",
        "en": "Management Consulting",
        "es": "Consultoría de gestión"
    },
    "Unfallversicherungsberatung": {
        "de": "Unfallversicherungsberatung",
        "en": "Accident Insurance Consulting",
        "es": "Asesoría de seguros de accidentes"
    },
    "Verhandlungsberatung": {
        "de": "Verhandlungsberatung",
        "en": "Negotiation Consulting",
        "es": "Consultoría de negociación"
    },
    "Venture-Capital-Beratung": {
        "de": "Venture-Capital-Beratung",
        "en": "Venture Capital Consulting",
        "es": "Consultoría de capital riesgo"
    },
    "Versicherungsberatung": {
        "de": "Versicherungsberatung",
        "en": "Insurance Consulting",
        "es": "Asesoría de seguros"
    },
    "Vertriebsberatung": {
        "de": "Vertriebsberatung",
        "en": "Sales Consulting",
        "es": "Consultoría de ventas"
    },
    "Vermögensschadenhaftpflichtversicherung": {
        "de": "Vermögensschadenhaftpflichtversicherung",
        "en": "Pecuniary Damage Liability Insurance",
        "es": "Seguro de responsabilidad patrimonial"
    },
    "Versorgungskonzept-Beratung": {
        "de": "Versorgungskonzept-Beratung",
        "en": "Pension Concept Consulting",
        "es": "Consultoría de conceptos de previsión"
    },
    "Zusatzversicherungsberatung": {
        "de": "Zusatzversicherungsberatung",
        "en": "Supplementary Insurance Consulting",
        "es": "Asesoría de seguros complementarios"
    },
    "Zuschussberatung": {
        "de": "Zuschussberatung",
        "en": "Grant Consulting",
        "es": "Asesoría de subvenciones"
    },
    "Abenteuercamps": {
        "de": "Abenteuercamps",
        "en": "Adventure Camps",
        "es": "Campamentos de aventura"
    },
    "Abenteuertouren": {
        "de": "Abenteuertouren",
        "en": "Adventure Tours",
        "es": "Tours de aventura"
    },
    "Aktivurlaub": {
        "de": "Aktivurlaub",
        "en": "Active Holidays",
        "es": "Vacaciones activas"
    },
    "All-Inclusive-Pakete": {
        "de": "All-Inclusive-Pakete",
        "en": "All-Inclusive Packages",
        "es": "Paquetes todo incluido"
    },
    "Autovermietung": {
        "de": "Autovermietung",
        "en": "Car Rental",
        "es": "Alquiler de coches"
    },
    "Backpacking": {
        "de": "Backpacking",
        "en": "Backpacking",
        "es": "Mochileros"
    },
    "Bergtouren": {
        "de": "Bergtouren",
        "en": "Mountain Tours",
        "es": "Excursiones de montaña"
    },
    "Campingreisen": {
        "de": "Campingreisen",
        "en": "Camping Trips",
        "es": "Viajes de camping"
    },
    "Erlebnisreisen": {
        "de": "Erlebnisreisen",
        "en": "Experience Travel",
        "es": "Viajes de experiencia"
    },
    "Expeditionen": {
        "de": "Expeditionen",
        "en": "Expeditions",
        "es": "Expediciones"
    },
    "Fahrradtouren": {
        "de": "Fahrradtouren",
        "en": "Bicycle Tours",
        "es": "Tours en bicicleta"
    },
    "Familienurlaubsreisen": {
        "de": "Familienurlaubsreisen",
        "en": "Family Holidays",
        "es": "Vacaciones familiares"
    },
    "Flitterwochen-Reisen": {
        "de": "Flitterwochen-Reisen",
        "en": "Honeymoon Trips",
        "es": "Viajes de luna de miel"
    },
    "Flugreservierungen": {
        "de": "Flugreservierungen",
        "en": "Flight Reservations",
        "es": "Reservas de vuelos"
    },
    "Flugtouren": {
        "de": "Flugtouren",
        "en": "Air Tours",
        "es": "Tours aéreos"
    },
    "Fotoreisen": {
        "de": "Fotoreisen",
        "en": "Photography Tours",
        "es": "Viajes fotográficos"
    },
    "Freizeitparks und Resorts": {
        "de": "Freizeitparks und Resorts",
        "en": "Theme Parks & Resorts",
        "es": "Parques temáticos y resorts"
    },
    "Geschäftsreisen": {
        "de": "Geschäftsreisen",
        "en": "Business Travel",
        "es": "Viajes de negocios"
    },
    "Incentive-Reisen": {
        "de": "Incentive-Reisen",
        "en": "Incentive Travel",
        "es": "Viajes de incentivos"
    },
    "Junggesellenabschiedsreisen": {
        "de": "Junggesellenabschiedsreisen",
        "en": "Bachelor Party Trips",
        "es": "Despedidas de soltero/a"
    },
    "Koch- und Gourmetreisen": {
        "de": "Koch- und Gourmetreisen",
        "en": "Culinary Tours",
        "es": "Viajes gastronómicos"
    },
    "Kreuzfahrten": {
        "de": "Kreuzfahrten",
        "en": "Cruises",
        "es": "Cruceros"
    },
    "Kultur- und Kunstreisen": {
        "de": "Kultur- und Kunstreisen",
        "en": "Culture & Art Tours",
        "es": "Viajes culturales y de arte"
    },
    "Kulturreisen": {
        "de": "Kulturreisen",
        "en": "Cultural Trips",
        "es": "Viajes culturales"
    },
    "Luxusreisen": {
        "de": "Luxusreisen",
        "en": "Luxury Travel",
        "es": "Viajes de lujo"
    },
    "Motorradtouren": {
        "de": "Motorradtouren",
        "en": "Motorcycle Tours",
        "es": "Tours en motocicleta"
    },
    "Nationalparks-Touren": {
        "de": "Nationalparks-Touren",
        "en": "National Park Tours",
        "es": "Tours a parques nacionales"
    },
    "Öko-Luxusreisen": {
        "de": "Öko-Luxusreisen",
        "en": "Eco-Luxury Travel",
        "es": "Viajes de eco-lujo"
    },
    "Öko-Touren": {
        "de": "Öko-Touren",
        "en": "Eco-Tours",
        "es": "Eco-tours"
    },
    "Ökotourismus-Reisen": {
        "de": "Ökotourismus-Reisen",
        "en": "Ecotourism Trips",
        "es": "Viajes de ecoturismo"
    },
    "Reisebüros": {
        "de": "Reisebüros",
        "en": "Travel Agencies",
        "es": "Agencias de viajes"
    },
    "Reiseversicherungen": {
        "de": "Reiseversicherungen",
        "en": "Travel Insurance",
        "es": "Seguros de viaje"
    },
    "Rucksacktouren": {
        "de": "Rucksacktouren",
        "en": "Backpacking Tours",
        "es": "Excursiones con mochila"
    },
    "Rundreisen": {
        "de": "Rundreisen",
        "en": "Round Trips",
        "es": "Circuitos"
    },
    "Safari-Reisen": {
        "de": "Safari-Reisen",
        "en": "Safari Trips",
        "es": "Safaris"
    },
    "Schiffsreisen": {
        "de": "Schiffsreisen",
        "en": "Boat Trips",
        "es": "Viajes en barco"
    },
    "Segelreisen": {
        "de": "Segelreisen",
        "en": "Sailing Trips",
        "es": "Viajes en velero"
    },
    "Skireisen": {
        "de": "Skireisen",
        "en": "Ski Trips",
        "es": "Viajes de esquí"
    },
    "Sprachreisen": {
        "de": "Sprachreisen",
        "en": "Language Trips",
        "es": "Viajes de idiomas"
    },
    "Städtereisen": {
        "de": "Städtereisen",
        "en": "City Breaks",
        "es": "Escapadas urbanas"
    },
    "Strandreisen": {
        "de": "Strandreisen",
        "en": "Beach Holidays",
        "es": "Vacaciones en la playa"
    },
    "Studienreisen": {
        "de": "Studienreisen",
        "en": "Study Trips",
        "es": "Viajes de estudio"
    },
    "Studentenreisen": {
        "de": "Studentenreisen",
        "en": "Student Trips",
        "es": "Viajes de estudiantes"
    },
    "Touristische Ausflüge": {
        "de": "Touristische Ausflüge",
        "en": "Tourist Excursions",
        "es": "Excursiones turísticas"
    },
    "Wander- und Trekkingreisen": {
        "de": "Wander- und Trekkingreisen",
        "en": "Hiking & Trekking Trips",
        "es": "Senderismo y trekking"
    },
    "Wanderreisen": {
        "de": "Wanderreisen",
        "en": "Hiking Trips",
        "es": "Viajes de senderismo"
    },
    "Wassersport-Touren": {
        "de": "Wassersport-Touren",
        "en": "Water Sports Tours",
        "es": "Tours de deportes acuáticos"
    },
    "Weltreisen": {
        "de": "Weltreisen",
        "en": "World Tours",
        "es": "Vuelta al mundo"
    },
    "Wüstentouren": {
        "de": "Wüstentouren",
        "en": "Desert Tours",
        "es": "Tours por el desierto"
    },
    "Zugreisen": {
        "de": "Zugreisen",
        "en": "Train Journeys",
        "es": "Viajes en tren"
    },
    "Autobusreisen": {
        "de": "Autobusreisen",
        "en": "Bus Tours",
        "es": "Viajes en autobús"
    },
    "Autoreparaturdienste": {
        "de": "Autoreparaturdienste",
        "en": "Car Repair Services",
        "es": "Servicios de reparación de automóviles"
    },
    "Autovermietung für Touristen": {
        "de": "Autovermietung für Touristen",
        "en": "Tourist Car Rental",
        "es": "Alquiler de coches para turistas"
    },
    "Autovermietungen für Langzeit": {
        "de": "Autovermietungen für Langzeit",
        "en": "Long-term Car Rental",
        "es": "Alquiler de coches a largo plazo"
    },
    "Bahnreisen": {
        "de": "Bahnreisen",
        "en": "Train Travel",
        "es": "Viajes en tren"
    },
    "Binnenschifffahrt": {
        "de": "Binnenschifffahrt",
        "en": "Inland Navigation",
        "es": "Navegación fluvial"
    },
    "Busreisen": {
        "de": "Busreisen",
        "en": "Bus Travel",
        "es": "Viajes en autobús"
    },
    "Carsharing-Dienste": {
        "de": "Carsharing-Dienste",
        "en": "Car Sharing Services",
        "es": "Servicios de carsharing"
    },
    "Containertransporte": {
        "de": "Containertransporte",
        "en": "Container Transport",
        "es": "Transporte de contenedores"
    },
    "Elektrofahrzeuge": {
        "de": "Elektrofahrzeuge",
        "en": "Electric Vehicles",
        "es": "Vehículos eléctricos"
    },
    "Elektromopedverleih": {
        "de": "Elektromopedverleih",
        "en": "Electric Moped Rental",
        "es": "Alquiler de ciclomotores eléctricos"
    },
    "Eisenbahnen": {
        "de": "Eisenbahnen",
        "en": "Railways",
        "es": "Ferrocarriles"
    },
    "Fahrradkurierdienste": {
        "de": "Fahrradkurierdienste",
        "en": "Bicycle Courier Services",
        "es": "Servicios de mensajería en bicicleta"
    },
    "Fahrradverleih": {
        "de": "Fahrradverleih",
        "en": "Bicycle Rental",
        "es": "Alquiler de bicicletas"
    },
    "Fahrdienste für Senioren": {
        "de": "Fahrdienste für Senioren",
        "en": "Senior Transport Services",
        "es": "Servicios de transporte para mayores"
    },
    "Fahrzeugvermietung": {
        "de": "Fahrzeugvermietung",
        "en": "Vehicle Rental",
        "es": "Alquiler de vehículos"
    },
    "Fährdienste": {
        "de": "Fährdienste",
        "en": "Ferry Services",
        "es": "Servicios de ferry"
    },
    "Flughafentransfers": {
        "de": "Flughafentransfers",
        "en": "Airport Transfers",
        "es": "Traslados al aeropuerto"
    },
    "Frachttransport": {
        "de": "Frachttransport",
        "en": "Freight Transport",
        "es": "Transporte de carga"
    },
    "Güterzugdienste": {
        "de": "Güterzugdienste",
        "en": "Freight Train Services",
        "es": "Servicios de trenes de carga"
    },
    "Helikopter-Transfers": {
        "de": "Helikopter-Transfers",
        "en": "Helicopter Transfers",
        "es": "Traslados en helicóptero"
    },
    "Kurierlogistik": {
        "de": "Kurierlogistik",
        "en": "Courier Logistics",
        "es": "Logística de mensajería"
    },
    "Lastwagenverleih": {
        "de": "Lastwagenverleih",
        "en": "Truck Rental",
        "es": "Alquiler de camiones"
    },
    "Lieferwagenvermietung": {
        "de": "Lieferwagenvermietung",
        "en": "Van Rental",
        "es": "Alquiler de furgonetas"
    },
    "Limousinenservice": {
        "de": "Limousinenservice",
        "en": "Limousine Service",
        "es": "Servicio de limusina"
    },
    "Logistikdienste": {
        "de": "Logistikdienste",
        "en": "Logistics Services",
        "es": "Servicios de logística"
    },
    "Luftfrachtlogistik": {
        "de": "Luftfrachtlogistik",
        "en": "Air Freight Logistics",
        "es": "Logística de carga aérea"
    },
    "Lufttransport": {
        "de": "Lufttransport",
        "en": "Air Transport",
        "es": "Transporte aéreo"
    },
    "Lkw-Logistikdienste": {
        "de": "Lkw-Logistikdienste",
        "en": "Truck Logistics Services",
        "es": "Servicios de logística de camiones"
    },
    "Mopedverleih": {
        "de": "Mopedverleih",
        "en": "Moped Rental",
        "es": "Alquiler de ciclomotores"
    },
    "Motorradverleih": {
        "de": "Motorradverleih",
        "en": "Motorcycle Rental",
        "es": "Alquiler de motocicletas"
    },
    "Parkplatz-Shuttleservices": {
        "de": "Parkplatz-Shuttleservices",
        "en": "Parking Shuttle Services",
        "es": "Servicios de transporte al aparcamiento"
    },
    "Privatflugzeugvermietung": {
        "de": "Privatflugzeugvermietung",
        "en": "Private Jet Rental",
        "es": "Alquiler de aviones privados"
    },
    "Ride-Sharing-Dienste": {
        "de": "Ride-Sharing-Dienste",
        "en": "Ride-Sharing Services",
        "es": "Servicios de viaje compartido"
    },
    "Rikscha-Verleih": {
        "de": "Rikscha-Verleih",
        "en": "Rickshaw Rental",
        "es": "Alquiler de rickshaws"
    },
    "Schulbusse": {
        "de": "Schulbusse",
        "en": "School Buses",
        "es": "Autobuses escolares"
    },
    "Schultransport": {
        "de": "Schultransport",
        "en": "School Transport",
        "es": "Transporte escolar"
    },
    "Schiffsverleih": {
        "de": "Schiffsverleih",
        "en": "Boat Rental",
        "es": "Alquiler de barcos"
    },
    "Schnelltransporte": {
        "de": "Schnelltransporte",
        "en": "Express Transport",
        "es": "Transporte urgente"
    },
    "Seetransport": {
        "de": "Seetransport",
        "en": "Sea Transport",
        "es": "Transporte marítimo"
    },
    "Shuttleservices": {
        "de": "Shuttleservices",
        "en": "Shuttle Services",
        "es": "Servicios de transporte"
    },
    "Stadtbusse": {
        "de": "Stadtbusse",
        "en": "City Buses",
        "es": "Autobuses urbanos"
    },
    "Straßenbahndienste": {
        "de": "Straßenbahndienste",
        "en": "Tram Services",
        "es": "Servicios de tranvía"
    },
    "Taxi-Dienste": {
        "de": "Taxi-Dienste",
        "en": "Taxi Services",
        "es": "Servicios de taxi"
    },
    "Transportdienst für Events": {
        "de": "Transportdienst für Events",
        "en": "Event Transport Services",
        "es": "Transporte para eventos"
    },
    "Transportdienste für Umzüge": {
        "de": "Transportdienste für Umzüge",
        "en": "Moving Transport Services",
        "es": "Transporte de mudanzas"
    },
    "Transporte für Schwerlast": {
        "de": "Transporte für Schwerlast",
        "en": "Heavy Load Transport",
        "es": "Transporte de carga pesada"
    },
    "Wassertransporte": {
        "de": "Wassertransporte",
        "en": "Water Transport",
        "es": "Transporte acuático"
    },
    "Zugfrachtlogistik": {
        "de": "Zugfrachtlogistik",
        "en": "Rail Freight Logistics",
        "es": "Logística de carga ferroviaria"
    }
}